mcp_kubectl/__init__.py
mcp_kubectl/cli.py
mcp_kubectl/mcp_server.py
mcp_kubectl/core/kubernetes_ops.py
mcp_kubectl-1.1.0.dist-info/METADATA
mcp_kubectl-1.1.0.dist-info/WHEEL
mcp_kubectl-1.1.0.dist-info/entry_points.txt
mcp_kubectl-1.1.0.dist-info/licenses/LICENSE
mcp_kubectl-1.1.0.dist-info/RECORD
