Metadata-Version: 2.4
Name: mcp-kubectl
Version: 1.1.0
Summary: A Model Context Protocol (MCP) server for Kubernetes
Project-URL: Homepage, https://github.com/rohitg00/kubectl-mcp-server
Project-URL: Documentation, https://github.com/rohitg00/kubectl-mcp-server/blob/main/docs/README.md
Project-URL: Repository, https://github.com/rohitg00/kubectl-mcp-server.git
Project-URL: Issues, https://github.com/rohitg00/kubectl-mcp-server/issues
Project-URL: Changelog, https://github.com/rohitg00/kubectl-mcp-server/blob/main/CHANGES.md
Author-email: Rohit Ghumare <your.email@example.com>
License-Expression: Apache-2.0
License-File: LICENSE
Keywords: ai,kubectl,kubernetes,mcp,model-context-protocol
Classifier: Development Status :: 4 - Beta
Classifier: Intended Audience :: Developers
Classifier: License :: OSI Approved :: Apache Software License
Classifier: Operating System :: OS Independent
Classifier: Programming Language :: Python :: 3
Classifier: Programming Language :: Python :: 3.10
Classifier: Programming Language :: Python :: 3.11
Classifier: Programming Language :: Python :: 3.12
Classifier: Topic :: Software Development :: Libraries :: Python Modules
Classifier: Topic :: System :: Systems Administration
Classifier: Topic :: Utilities
Requires-Python: >=3.10
Requires-Dist: aiohttp-sse>=2.1.0
Requires-Dist: aiohttp>=3.8.0
Requires-Dist: cryptography>=42.0.2
Requires-Dist: fastapi>=0.100.0
Requires-Dist: jsonschema>=4.20.0
Requires-Dist: kubernetes>=28.1.0
Requires-Dist: mcp>=1.5.0
Requires-Dist: pydantic>=2.0.0
Requires-Dist: pyyaml>=6.0.1
Requires-Dist: requests>=2.31.0
Requires-Dist: rich>=13.0.0
Requires-Dist: urllib3>=2.1.0
Requires-Dist: uvicorn>=0.22.0
Requires-Dist: websocket-client>=1.7.0
